Backup2Cloud/Backup2Cloud.ini
Backup2Cloud/__init__.py
Backup2Cloud/__main__.py
Backup2Cloud/gdrive.py
Backup2Cloud/providers/__init__.py
Backup2Cloud/providers/folder.py
Backup2Cloud/providers/gdrive.py
Backup2Cloud/providers/providersinterface.py
Backup2Cloud-1.0.17.dist-info/LICENSE
Backup2Cloud-1.0.17.dist-info/METADATA
Backup2Cloud-1.0.17.dist-info/WHEEL
Backup2Cloud-1.0.17.dist-info/top_level.txt
Backup2Cloud-1.0.17.dist-info/RECORD
