Metadata-Version: 2.1
Name: Backup2Cloud
Version: 1.0.17
Summary: Backup specific folders to and upload to a cloud provider
Home-page: https://github.com/otapi/Backup2Cloud
Author: otapi
License: UNKNOWN
Platform: UNKNOWN
Classifier: Programming Language :: Python :: 3
Classifier: License :: OSI Approved :: Apache Software License
Classifier: Operating System :: OS Independent
Requires-Python: >=3.7.3
Requires-Dist: google-api-python-client
Requires-Dist: google-auth-httplib2
Requires-Dist: google-auth-oauthlib
Requires-Dist: py7zr
Requires-Dist: dirtools2
